Metadata-Version: 1.1
Name: antivaxxtweetanalyzer
Version: 0.0.1
Summary: Identify if a Twitter account displays anti-vaccine sentiment.
Home-page: UNKNOWN
Author: Matheus Schmitz
Author-email: mschmitz@usc.edu
License: UNKNOWN
Platform: UNKNOWN
Classifier: Operating System :: OS Independent
Classifier: License :: OSI Approved :: MIT License
Classifier: Programming Language :: Python :: 3
